cyclicpattern/__init__.py
cyclicpattern/cli.py
cyclic_pattern-0.0.2.dist-info/METADATA
cyclic_pattern-0.0.2.dist-info/WHEEL
cyclic_pattern-0.0.2.dist-info/entry_points.txt
cyclic_pattern-0.0.2.dist-info/top_level.txt
cyclic_pattern-0.0.2.dist-info/RECORD
